{
  "description": "班級名稱 → Level 對照表 (84 classes, 2025-2026 學年)",
  "academicYear": "2025-2026",
  "totalClasses": 84,
  "classes": {
    "G1 Achievers": "G1E1",
    "G1 Discoverers": "G1E1",
    "G1 Voyagers": "G1E1",
    "G1 Explorers": "G1E1",
    "G1 Navigators": "G1E1",
    "G1 Adventurers": "G1E2",
    "G1 Guardians": "G1E2",
    "G1 Pioneers": "G1E2",
    "G1 Innovators": "G1E2",
    "G1 Visionaries": "G1E2",
    "G1 Pathfinders": "G1E3",
    "G1 Seekers": "G1E3",
    "G1 Trailblazers": "G1E3",
    "G1 Inventors": "G1E3",

    "G2 Pioneers": "G2E1",
    "G2 Explorers": "G2E1",
    "G2 Inventors": "G2E1",
    "G2 Achievers": "G2E1",
    "G2 Voyagers": "G2E1",
    "G2 Adventurers": "G2E2",
    "G2 Innovators": "G2E2",
    "G2 Guardians": "G2E2",
    "G2 Pathfinders": "G2E2",
    "G2 Visionaries": "G2E2",
    "G2 Navigators": "G2E3",
    "G2 Discoverers": "G2E3",
    "G2 Seekers": "G2E3",
    "G2 Trailblazers": "G2E3",

    "G3 Inventors": "G3E1",
    "G3 Innovators": "G3E1",
    "G3 Guardians": "G3E1",
    "G3 Achievers": "G3E1",
    "G3 Voyagers": "G3E2",
    "G3 Visionaries": "G3E2",
    "G3 Trailblazers": "G3E2",
    "G3 Discoverers": "G3E2",
    "G3 Explorers": "G3E2",
    "G3 Navigators": "G3E2",
    "G3 Adventurers": "G3E2",
    "G3 Seekers": "G3E3",
    "G3 Pathfinders": "G3E3",
    "G3 Pioneers": "G3E3",

    "G4 Seekers": "G4E1",
    "G4 Voyagers": "G4E1",
    "G4 Visionaries": "G4E1",
    "G4 Achievers": "G4E1",
    "G4 Navigators": "G4E2",
    "G4 Trailblazers": "G4E2",
    "G4 Pathfinders": "G4E2",
    "G4 Explorers": "G4E2",
    "G4 Adventurers": "G4E2",
    "G4 Innovators": "G4E2",
    "G4 Discoverers": "G4E2",
    "G4 Guardians": "G4E3",
    "G4 Inventors": "G4E3",
    "G4 Pioneers": "G4E3",

    "G5 Adventurers": "G5E1",
    "G5 Navigators": "G5E1",
    "G5 Pioneers": "G5E1",
    "G5 Inventors": "G5E2",
    "G5 Seekers": "G5E2",
    "G5 Discoverers": "G5E2",
    "G5 Guardians": "G5E2",
    "G5 Pathfinders": "G5E2",
    "G5 Explorers": "G5E2",
    "G5 Achievers": "G5E2",
    "G5 Voyagers": "G5E3",
    "G5 Trailblazers": "G5E3",
    "G5 Innovators": "G5E3",
    "G5 Visionaries": "G5E3",

    "G6 Explorers": "G6E1",
    "G6 Inventors": "G6E1",
    "G6 Adventurers": "G6E1",
    "G6 Achievers": "G6E1",
    "G6 Voyagers": "G6E2",
    "G6 Discoverers": "G6E2",
    "G6 Innovators": "G6E2",
    "G6 Guardians": "G6E2",
    "G6 Pathfinders": "G6E2",
    "G6 Seekers": "G6E2",
    "G6 Visionaries": "G6E2",
    "G6 Pioneers": "G6E3",
    "G6 Trailblazers": "G6E3",
    "G6 Navigators": "G6E3"
  },
  "levelDistribution": {
    "G1": { "E1": 5, "E2": 5, "E3": 4, "total": 14 },
    "G2": { "E1": 5, "E2": 5, "E3": 4, "total": 14 },
    "G3": { "E1": 4, "E2": 7, "E3": 3, "total": 14 },
    "G4": { "E1": 4, "E2": 7, "E3": 3, "total": 14 },
    "G5": { "E1": 3, "E2": 7, "E3": 4, "total": 14 },
    "G6": { "E1": 4, "E2": 7, "E3": 3, "total": 14 }
  }
}
